alo/__init__.py
alo/decorators.py
alo/fields.py
alo/forms.py
alo/mixins.py
alo/models.py
alo/operators.py
alo/tests.py
django_alo_forms-1.9.3.dist-info/DESCRIPTION.rst
django_alo_forms-1.9.3.dist-info/METADATA
django_alo_forms-1.9.3.dist-info/metadata.json
django_alo_forms-1.9.3.dist-info/RECORD
django_alo_forms-1.9.3.dist-info/top_level.txt
django_alo_forms-1.9.3.dist-info/WHEEL
