Metadata-Version: 2.0
Name: django-alo-forms
Version: 1.9.3
Summary: Additional Logic on Forms
Home-page: https://github.com/laginha/django-alo-forms
Author: Diogo Laginha
Author-email: diogo.laginha.machado@gmail.com
License: MIT
Platform: UNKNOWN
Classifier: License :: OSI Approved :: MIT License
Classifier: Programming Language :: Python :: 2
Classifier: Intended Audience :: Developers
Requires-Dist: django
Requires-Dist: django-easy-response
